mcs/__init__.py
mcs/api_client.py
mcs/main.py
mcs/security.py
mcs-0.0.9.dist-info/LICENSE
mcs-0.0.9.dist-info/METADATA
mcs-0.0.9.dist-info/WHEEL
mcs-0.0.9.dist-info/RECORD
